odoo/addons/l10n_th_account_tax_report/README.rst
odoo/addons/l10n_th_account_tax_report/__init__.py
odoo/addons/l10n_th_account_tax_report/__manifest__.py
odoo/addons/l10n_th_account_tax_report/data/paper_format.xml
odoo/addons/l10n_th_account_tax_report/data/report_data.xml
odoo/addons/l10n_th_account_tax_report/i18n/l10n_th_account_tax_report.pot
odoo/addons/l10n_th_account_tax_report/models/__init__.py
odoo/addons/l10n_th_account_tax_report/models/res_company.py
odoo/addons/l10n_th_account_tax_report/models/res_config_settings.py
odoo/addons/l10n_th_account_tax_report/readme/CONFIGURE.md
odoo/addons/l10n_th_account_tax_report/readme/CONTRIBUTORS.md
odoo/addons/l10n_th_account_tax_report/readme/DESCRIPTION.md
odoo/addons/l10n_th_account_tax_report/readme/USAGE.md
odoo/addons/l10n_th_account_tax_report/reports/__init__.py
odoo/addons/l10n_th_account_tax_report/reports/tax_report.py
odoo/addons/l10n_th_account_tax_report/reports/tax_report_rd.py
odoo/addons/l10n_th_account_tax_report/reports/tax_report_xlsx.py
odoo/addons/l10n_th_account_tax_report/reports/wht_report.py
odoo/addons/l10n_th_account_tax_report/reports/wht_report_rd.py
odoo/addons/l10n_th_account_tax_report/reports/wht_report_text.py
odoo/addons/l10n_th_account_tax_report/reports/wht_report_xlsx.py
odoo/addons/l10n_th_account_tax_report/reports/templates/tax_report.xml
odoo/addons/l10n_th_account_tax_report/reports/templates/tax_report_rd.xml
odoo/addons/l10n_th_account_tax_report/reports/templates/wht_report.xml
odoo/addons/l10n_th_account_tax_report/reports/templates/wht_report_rd.xml
odoo/addons/l10n_th_account_tax_report/reports/templates/wht_report_rd_pnd1.xml
odoo/addons/l10n_th_account_tax_report/reports/templates/wht_report_rd_pnd1a.xml
odoo/addons/l10n_th_account_tax_report/reports/templates/wht_report_rd_pnd2.xml
odoo/addons/l10n_th_account_tax_report/reports/templates/wht_report_rd_pnd3.xml
odoo/addons/l10n_th_account_tax_report/reports/templates/wht_report_rd_pnd53.xml
odoo_addon_l10n_th_account_tax_report-18.0.1.0.0.3.dist-info/METADATA
odoo_addon_l10n_th_account_tax_report-18.0.1.0.0.3.dist-info/WHEEL
odoo_addon_l10n_th_account_tax_report-18.0.1.0.0.3.dist-info/top_level.txt
odoo_addon_l10n_th_account_tax_report-18.0.1.0.0.3.dist-info/RECORD
