Metadata-Version: 2.1
Name: odoo-addon-l10n_th_account_tax_report
Version: 18.0.1.0.0.3
Requires-Python: >=3.10
Requires-Dist: odoo-addon-date_range==18.0.*
Requires-Dist: odoo-addon-l10n_th_account_tax==18.0.*
Requires-Dist: odoo-addon-l10n_th_base_utils==18.0.*
Requires-Dist: odoo-addon-l10n_th_partner==18.0.*
Requires-Dist: odoo-addon-report_xlsx_helper==18.0.*
Requires-Dist: odoo==18.0.*
Summary: Thai Localization - VAT and Withholding Tax Reports
Home-page: https://github.com/OCA/l10n-thailand
License: AGPL-3
Author: Ecosoft, Odoo Community Association (OCA)
Author-email: support@odoo-community.org
Classifier: Programming Language :: Python
Classifier: Framework :: Odoo
Classifier: Framework :: Odoo :: 18.0
Classifier: License :: OSI Approved :: GNU Affero General Public License v3
Classifier: Development Status :: 4 - Beta
